driverlessai-2.3.1.dist-info/METADATA
driverlessai-2.3.1.dist-info/WHEEL
driverlessai-2.3.1.dist-info/entry_points.txt
driverlessai-2.3.1.dist-info/licenses/LICENSE
driverlessai/BUILD_INFO.txt
driverlessai/__about__.py
driverlessai/__init__.py
driverlessai/_admin.py
driverlessai/_autodoc.py
driverlessai/_autoviz.py
driverlessai/_common_metric_plots.py
driverlessai/_commons.py
driverlessai/_commons_mli.py
driverlessai/_core.py
driverlessai/_datasets.py
driverlessai/_deployments.py
driverlessai/_enums.py
driverlessai/_exceptions.py
driverlessai/_experiments.py
driverlessai/_h2oai_client.py
driverlessai/_h2oai_client_1_10_0/BUILD_INFO.txt
driverlessai/_h2oai_client_1_10_0/__about__.py
driverlessai/_h2oai_client_1_10_0/__init__.py
driverlessai/_h2oai_client_1_10_0/messages.py
driverlessai/_h2oai_client_1_10_0/protocol.py
driverlessai/_h2oai_client_1_10_0/references.py
driverlessai/_h2oai_client_1_10_0/validation.py
driverlessai/_h2oai_client_1_10_1/BUILD_INFO.txt
driverlessai/_h2oai_client_1_10_1/__about__.py
driverlessai/_h2oai_client_1_10_1/__init__.py
driverlessai/_h2oai_client_1_10_1/messages.py
driverlessai/_h2oai_client_1_10_1/protocol.py
driverlessai/_h2oai_client_1_10_1/references.py
driverlessai/_h2oai_client_1_10_1/validation.py
driverlessai/_h2oai_client_1_10_1_1/BUILD_INFO.txt
driverlessai/_h2oai_client_1_10_1_1/__about__.py
driverlessai/_h2oai_client_1_10_1_1/__init__.py
driverlessai/_h2oai_client_1_10_1_1/messages.py
driverlessai/_h2oai_client_1_10_1_1/protocol.py
driverlessai/_h2oai_client_1_10_1_1/references.py
driverlessai/_h2oai_client_1_10_1_1/validation.py
driverlessai/_h2oai_client_1_10_1_2/BUILD_INFO.txt
driverlessai/_h2oai_client_1_10_1_2/__about__.py
driverlessai/_h2oai_client_1_10_1_2/__init__.py
driverlessai/_h2oai_client_1_10_1_2/messages.py
driverlessai/_h2oai_client_1_10_1_2/protocol.py
driverlessai/_h2oai_client_1_10_1_2/references.py
driverlessai/_h2oai_client_1_10_1_2/validation.py
driverlessai/_h2oai_client_1_10_1_3/BUILD_INFO.txt
driverlessai/_h2oai_client_1_10_1_3/__about__.py
driverlessai/_h2oai_client_1_10_1_3/__init__.py
driverlessai/_h2oai_client_1_10_1_3/messages.py
driverlessai-2.3.1.dist-info/RECORD
