Metadata-Version: 2.1
Name: driverlessai
Version: 2.3.1
Summary: Python client for H2O Driverless AI.
Keywords: h2o,driverless,ai,client,automl,machine learning,data science,artificial intelligence
Author-Email: "H2O.ai" <support@h2o.ai>
License: 
Classifier: Development Status :: 5 - Production/Stable
Classifier: Programming Language :: Python :: 3.8
Classifier: Programming Language :: Python :: 3.9
Classifier: Programming Language :: Python :: 3.10
Classifier: Programming Language :: Python :: 3.11
Classifier: Programming Language :: Python :: 3.12
Project-URL: Homepage, https://h2o.ai/products/h2o-driverless-ai/
Project-URL: Documentation, https://docs.h2o.ai/driverless-ai/pyclient/docs/html/index.html
Project-URL: Changelog, https://docs.h2o.ai/driverless-ai/pyclient/docs/html/CHANGELOG.html
Requires-Python: >=3.8
Requires-Dist: requests
Requires-Dist: urllib3>=1.26.0
Requires-Dist: tabulate
Requires-Dist: toml
Requires-Dist: packaging>=21.0
Provides-Extra: optional
Requires-Dist: fsspec>=2024.5.0; extra == "optional"
Requires-Dist: pandas; extra == "optional"
